DESCRIPTION.rst
MANIFEST.in
README.rst
setup.cfg
setup.py
data/data_file
data/grafana_alerts.cfg
data/html_version_item.html
data/html_version_main.html
grafana_alerts/__init__.py
grafana_alerts/alerting.py
grafana_alerts/html_version_item.html
grafana_alerts/html_version_main.html
grafana_alerts/launcher.py
grafana_alerts/package_data.dat
grafana_alerts/reporting.py
grafana_alerts.egg-info/PKG-INFO
grafana_alerts.egg-info/SOURCES.txt
grafana_alerts.egg-info/dependency_links.txt
grafana_alerts.egg-info/entry_points.txt
grafana_alerts.egg-info/requires.txt
grafana_alerts.egg-info/top_level.txt