Metadata-Version: 1.1
Name: grafana-alerts
Version: 1.0.0.dev7
Summary: Alerting Module to use with Grafana metrics.
Home-page: https://github.com/pabloa/grafana-alerts
Author: Pablo Alcaraz
Author-email: pabloa98@gmail.com
License: Apache License 2.0
Keywords: grafana alerts grafana_alerts grafana-alerts monitoring cluster
Platform: UNKNOWN
Classifier: Development Status :: 4 - Beta
Classifier: Intended Audience :: Developers
Classifier: Intended Audience :: Information Technology
Classifier: Intended Audience :: System Administrators
Classifier: Topic :: Internet :: Log Analysis
Classifier: Topic :: System :: Clustering
Classifier: Topic :: System :: Monitoring
Classifier: License :: OSI Approved :: Apache Software License
Classifier: Programming Language :: Python :: 2.6
Classifier: Programming Language :: Python :: 2.7
Classifier: Programming Language :: Python :: 3
Classifier: Programming Language :: Python :: 3.2
Classifier: Programming Language :: Python :: 3.3
Classifier: Programming Language :: Python :: 3.4
Classifier: Operating System :: POSIX
Classifier: Operating System :: POSIX :: AIX
Classifier: Operating System :: POSIX :: BSD
Classifier: Operating System :: POSIX :: BSD :: BSD/OS
Classifier: Operating System :: POSIX :: BSD :: FreeBSD
Classifier: Operating System :: POSIX :: BSD :: NetBSD
Classifier: Operating System :: POSIX :: BSD :: OpenBSD
Classifier: Operating System :: POSIX :: GNU Hurd
Classifier: Operating System :: POSIX :: HP-UX
Classifier: Operating System :: POSIX :: IRIX
Classifier: Operating System :: POSIX :: Linux
Classifier: Operating System :: POSIX :: Other
Classifier: Operating System :: POSIX :: SunOS/Solaris
Classifier: Operating System :: Unix
